mathbull/__init__.py
mathbull/mathbull.py
mathbull-1.0.0.dist-info/LICENSE
mathbull-1.0.0.dist-info/METADATA
mathbull-1.0.0.dist-info/WHEEL
mathbull-1.0.0.dist-info/top_level.txt
mathbull-1.0.0.dist-info/RECORD
